{
  "generated_at": "2026-07-15",
  "project_name": "growfase_system",
  "system": {
    "os": "Windows",
    "shell": "PowerShell"
  },
  "cli_tools": {
    "git": {
      "installed": true,
      "version": "2.50.1.windows.1"
    },
    "gh": {
      "installed": true,
      "version": "2.94.0",
      "authenticated": true,
      "account": "growfase"
    },
    "node": {
      "installed": true,
      "version": "22.14.0"
    },
    "npm": {
      "installed": true,
      "version": "11.14.1",
      "note": "Use npm.cmd in PowerShell because npm.ps1 is blocked by ExecutionPolicy."
    }
  },
  "repository": {
    "initialized": true,
    "remote_url": "https://github.com/growfase/growfase_system.git",
    "branch": "main"
  },
  "validation": {
    "ready_for_initial_commit": true,
    "initial_push_done": false
  }
}
